wagtailmarkdown/__init__.py
wagtailmarkdown/blocks.py
wagtailmarkdown/constants.py
wagtailmarkdown/fields.py
wagtailmarkdown/utils.py
wagtailmarkdown/warnings.py
wagtailmarkdown/widgets.py
wagtailmarkdown/mdx/__init__.py
wagtailmarkdown/mdx/inlinepatterns.py
wagtailmarkdown/mdx/linker/__init__.py
wagtailmarkdown/mdx/linkers/__init__.py
wagtailmarkdown/mdx/linkers/document.py
wagtailmarkdown/mdx/linkers/image.py
wagtailmarkdown/mdx/linkers/page.py
wagtailmarkdown/static/wagtailmarkdown/css/easymde.min.css
wagtailmarkdown/static/wagtailmarkdown/css/easymde.tweaks.css
wagtailmarkdown/static/wagtailmarkdown/js/easymde-controller.js
wagtailmarkdown/static/wagtailmarkdown/js/easymde.attach.js
wagtailmarkdown/static/wagtailmarkdown/js/easymde.min.js
wagtailmarkdown/static/wagtailmarkdown/js/markdown-textarea-adapter.js
wagtailmarkdown/templatetags/__init__.py
wagtailmarkdown/templatetags/wagtailmarkdown.py
wagtail_markdown-0.13.0.dist-info/licenses/LICENSE
wagtail_markdown-0.13.0.dist-info/WHEEL
wagtail_markdown-0.13.0.dist-info/METADATA
wagtail_markdown-0.13.0.dist-info/RECORD
