Metadata-Version: 2.4
Name: wagtail-markdown
Version: 0.13.0
Summary: Markdown support for Wagtail
Keywords: Wagtail,Django,Markdown
Author-email: Felicity Tarnell  <hello@torchbox.com>
Maintainer-email: Dan Braghis <dan.braghis@torchbox.com>
Requires-Python: >=3.9
Classifier: Development Status :: 4 - Beta
Classifier: Environment :: Web Environment
Classifier: Intended Audience :: Developers
Classifier: Operating System :: OS Independent
Classifier: License :: OSI Approved :: zlib/libpng License
Classifier: Programming Language :: Python
Classifier: Programming Language :: Python :: 3
Classifier: Programming Language :: Python :: 3.9
Classifier: Programming Language :: Python :: 3.10
Classifier: Programming Language :: Python :: 3.11
Classifier: Programming Language :: Python :: 3.12
Classifier: Programming Language :: Python :: 3.13
Classifier: Framework :: Django
Classifier: Framework :: Django :: 4.2
Classifier: Framework :: Django :: 5.1
Classifier: Framework :: Django :: 5.2
Classifier: Framework :: Wagtail
Classifier: Framework :: Wagtail :: 6
Classifier: Framework :: Wagtail :: 7
License-File: LICENSE
Requires-Dist: Wagtail>=6.3
Requires-Dist: Markdown>=3.3,<4
Requires-Dist: bleach>=3.3,<5
Requires-Dist: tox>=4.6.4,<5 ; extra == "testing"
Requires-Dist: coverage>=7.0,<8.0 ; extra == "testing"
Project-URL: Changelog, https://github.com/torchbox/wagtail-markdown/blob/main/CHANGELOG.md
Project-URL: Repository, https://github.com/torchbox/wagtail-markdown
Provides-Extra: testing
